vis_cli/__init__.py
vis_cli/cli.py
vis_cli-0.5.0.dist-info/METADATA
vis_cli-0.5.0.dist-info/WHEEL
vis_cli-0.5.0.dist-info/entry_points.txt
vis_cli-0.5.0.dist-info/RECORD
