Metadata-Version: 2.1
Name: vis_cli
Version: 0.5.0
Summary: Vis visualizes fuzzy tabular data, no script required
Author: Hunter Gatewood
Author-email: hgatewood@gmail.com
Requires-Python: >=3.12,<4.0
Classifier: Programming Language :: Python :: 3
Classifier: Programming Language :: Python :: 3.12
Requires-Dist: click (>=8.0.0,<9.0.0)
Requires-Dist: matplotlib (>=3.10,<4.0)
Requires-Dist: numpy (>=2.3,<3.0)
Requires-Dist: pytimeparse (>=1.1.8,<2.0.0)
Requires-Dist: scipy (>=1.16,<2.0)
Requires-Dist: seaborn (>=0.13,<0.14)
